{"data":{"getProductListing":{"totalCount":75,"edges":[{"node":{"id":"20","MNR":"Funktionserweiterung TCS:BUS","Geraeteart4077":"","Kommunikationstechnologie4164":"","Audio1":null,"Video2":true,"IP1":null,"PERIODE1":null,"TEXT":null,"parent":{"MNR":"Funktionserweiterung TCS:BUS"},"Audio":[{"features":[{"name":"AnzahlKlingeltasten3938","text":null},{"name":"AnzahlakustischerRufunterscheidungen3933","text":null},{"name":"Mikrofonabsetzbarin4292","text":null},{"name":"LautstaerkeGespraech4008","text":null},{"name":"AnzahlParallelrufe3892","text":null}]},{"features":[null]}]}},{"node":{"id":"1491","MNR":"BMN2-EB","Geraeteart4077":"Ausführen von Melde- und/oder Schaltfunktionen","Kommunikationstechnologie4164":"TCS:BUS","Audio1":null,"Video2":null,"IP1":null,"PERIODE1":125,"TEXT":null,"parent":{"MNR":"Funktionserweiterung TCS:BUS"},"Audio":[{"features":[{"name":"AnzahlKlingeltasten3938","text":null},{"name":"AnzahlakustischerRufunterscheidungen3933","text":null},{"name":"Mikrofonabsetzbarin4292","text":null},{"name":"LautstaerkeGespraech4008","text":null},{"name":"AnzahlParallelrufe3892","text":null}]}]}},{"node":{"id":"1492","MNR":"BRE2-EB","Geraeteart4077":"Ausführen von Melde- und/oder Schaltfunktionen","Kommunikationstechnologie4164":"TCS:BUS","Audio1":null,"Video2":null,"IP1":null,"PERIODE1":130,"TEXT":null,"parent":{"MNR":"Funktionserweiterung TCS:BUS"},"Audio":[{"features":[{"name":"AnzahlKlingeltasten3938","text":null},{"name":"AnzahlakustischerRufunterscheidungen3933","text":null},{"name":"Mikrofonabsetzbarin4292","text":null},{"name":"LautstaerkeGespraech4008","text":null},{"name":"AnzahlParallelrufe3892","text":null}]}]}},{"node":{"id":"1493","MNR":"BRE2-SG","Geraeteart4077":"Ausführen von Melde- und/oder Schaltfunktionen","Kommunikationstechnologie4164":"TCS:BUS","Audio1":null,"Video2":null,"IP1":null,"PERIODE1":130,"TEXT":null,"parent":{"MNR":"Funktionserweiterung TCS:BUS"},"Audio":[{"features":[{"name":"AnzahlKlingeltasten3938","text":null},{"name":"AnzahlakustischerRufunterscheidungen3933","text":null},{"name":"Mikrofonabsetzbarin4292","text":null},{"name":"LautstaerkeGespraech4008","text":null},{"name":"AnzahlParallelrufe3892","text":null}]}]}},{"node":{"id":"1801","MNR":"FAA1100-0600","Geraeteart4077":"Türöffner-Relais für gezieltes Türöffnen bei mehr als einer Außenstation","Kommunikationstechnologie4164":"TCS:BUS","Audio1":null,"Video2":null,"IP1":null,"PERIODE1":50,"TEXT":null,"parent":{"MNR":"Funktionserweiterung TCS:BUS"},"Audio":[{"features":[{"name":"AnzahlKlingeltasten3938","text":null},{"name":"AnzahlakustischerRufunterscheidungen3933","text":null},{"name":"Mikrofonabsetzbarin4292","text":null},{"name":"LautstaerkeGespraech4008","text":null},{"name":"AnzahlParallelrufe3892","text":null}]},{"features":[null,null,null,{"name":"VerwendungbeiAnzahl Wohneinheitenvon4938","text":null},{"name":"VerwendungbeiAnzahlWohneinheitenbis4939","text":null},{"name":"MAXmoeglicheLasteinheitenAUDIO","text":null}]},{"features":[{"name":"AnzahlKlingeltasten3938","text":null},null,null,null,null,{"name":"Mikrofonabsetzbarin4292","text":null},null,{"name":"LautstaerkeGespraech4008","text":null},null,null,null,null,null,null,null,null,null,null,null,null,null,null,{"name":"VerwendungbeiAnzahl Wohneinheitenvon4938","text":null},{"name":"VerwendungbeiAnzahlWohneinheitenbis4939","text":null},null,{"name":"AkustischeRufunterscheidungen","text":null},null,null,null,null,null]}]}},{"node":{"id":"1802","MNR":"FAA1200-0400","Geraeteart4077":"Türöffner-Relais für gezieltes Türöffnen bei mehr als einer Außenstation","Kommunikationstechnologie4164":"TCS:BUS","Audio1":true,"Video2":true,"IP1":null,"PERIODE1":90,"TEXT":null,"parent":{"MNR":"Funktionserweiterung TCS:BUS"},"Audio":[{"features":[{"name":"AnzahlKlingeltasten3938","text":null},{"name":"AnzahlakustischerRufunterscheidungen3933","text":null},{"name":"Mikrofonabsetzbarin4292","text":null},{"name":"LautstaerkeGespraech4008","text":null},{"name":"AnzahlParallelrufe3892","text":null}]},{"features":[null,null,null,{"name":"VerwendungbeiAnzahl Wohneinheitenvon4938","text":null},{"name":"VerwendungbeiAnzahlWohneinheitenbis4939","text":null},{"name":"MAXmoeglicheLasteinheitenAUDIO","text":null}]},{"features":[{"name":"AnzahlKlingeltasten3938","text":null},null,null,null,null,{"name":"Mikrofonabsetzbarin4292","text":null},null,{"name":"LautstaerkeGespraech4008","text":null},null,null,null,null,null,null,null,null,null,null,null,null,null,null,{"name":"VerwendungbeiAnzahl Wohneinheitenvon4938","text":null},{"name":"VerwendungbeiAnzahlWohneinheitenbis4939","text":null},null,{"name":"AkustischeRufunterscheidungen","text":null},null,null,null,null,null]}]}},{"node":{"id":"1805","MNR":"FAA1250-0400","Geraeteart4077":"Selektives Türöffner-Relais für gezieltes Türöffnen bei einer Außenstation","Kommunikationstechnologie4164":"TCS:BUS","Audio1":null,"Video2":null,"IP1":null,"PERIODE1":110,"TEXT":null,"parent":{"MNR":"Funktionserweiterung TCS:BUS"},"Audio":[{"features":[{"name":"AnzahlKlingeltasten3938","text":null},{"name":"AnzahlakustischerRufunterscheidungen3933","text":null},{"name":"Mikrofonabsetzbarin4292","text":null},{"name":"LautstaerkeGespraech4008","text":null},{"name":"AnzahlParallelrufe3892","text":null}]},{"features":[null,null,null,{"name":"VerwendungbeiAnzahl Wohneinheitenvon4938","text":null},{"name":"VerwendungbeiAnzahlWohneinheitenbis4939","text":null},{"name":"MAXmoeglicheLasteinheitenAUDIO","text":null}]},{"features":[{"name":"AnzahlKlingeltasten3938","text":null},null,null,null,null,{"name":"Mikrofonabsetzbarin4292","text":null},null,{"name":"LautstaerkeGespraech4008","text":null},null,null,null,null,null,null,null,null,null,null,null,null,null,null,{"name":"VerwendungbeiAnzahl Wohneinheitenvon4938","text":null},{"name":"VerwendungbeiAnzahlWohneinheitenbis4939","text":null},null,{"name":"AkustischeRufunterscheidungen","text":null},null,null,null,null,null]}]}},{"node":{"id":"1812","MNR":"FBA4100-0119","Geraeteart4077":"Etagentaster","Kommunikationstechnologie4164":"TCS:BUS","Audio1":null,"Video2":null,"IP1":null,"PERIODE1":156,"TEXT":null,"parent":{"MNR":"Funktionserweiterung TCS:BUS"},"Audio":[{"features":[{"name":"AnzahlKlingeltasten3938","text":"1"},{"name":"AnzahlakustischerRufunterscheidungen3933","text":null},{"name":"Mikrofonabsetzbarin4292","text":null},{"name":"LautstaerkeGespraech4008","text":null},{"name":"AnzahlParallelrufe3892","text":null}]}]}},{"node":{"id":"1813","MNR":"FBA4100-0210","Geraeteart4077":"Etagentaster","Kommunikationstechnologie4164":"TCS:BUS","Audio1":null,"Video2":null,"IP1":null,"PERIODE1":164,"TEXT":null,"parent":{"MNR":"Funktionserweiterung TCS:BUS"},"Audio":[{"features":[{"name":"AnzahlKlingeltasten3938","text":"1"},{"name":"AnzahlakustischerRufunterscheidungen3933","text":null},{"name":"Mikrofonabsetzbarin4292","text":null},{"name":"LautstaerkeGespraech4008","text":null},{"name":"AnzahlParallelrufe3892","text":null}]}]}},{"node":{"id":"1815","MNR":"FBC2000-0400","Geraeteart4077":"Zentralbuskoppler","Kommunikationstechnologie4164":"TCS:BUS","Audio1":null,"Video2":null,"IP1":null,"PERIODE1":378,"TEXT":null,"parent":{"MNR":"Funktionserweiterung TCS:BUS"},"Audio":[{"features":[{"name":"AnzahlKlingeltasten3938","text":null},{"name":"AnzahlakustischerRufunterscheidungen3933","text":null},{"name":"Mikrofonabsetzbarin4292","text":null},{"name":"LautstaerkeGespraech4008","text":null},{"name":"AnzahlParallelrufe3892","text":null}]}]}},{"node":{"id":"1817","MNR":"FBC3000-0600","Geraeteart4077":"Strangtrenner","Kommunikationstechnologie4164":"TCS:BUS","Audio1":null,"Video2":null,"IP1":null,"PERIODE1":109,"TEXT":null,"parent":{"MNR":"Funktionserweiterung TCS:BUS"},"Audio":[{"features":[{"name":"AnzahlKlingeltasten3938","text":null},{"name":"AnzahlakustischerRufunterscheidungen3933","text":null},{"name":"Mikrofonabsetzbarin4292","text":null},{"name":"LautstaerkeGespraech4008","text":null},{"name":"AnzahlParallelrufe3892","text":null}]}]}},{"node":{"id":"1819","MNR":"FBC3600-0400","Geraeteart4077":"Multistrangtrenner","Kommunikationstechnologie4164":"TCS:BUS","Audio1":null,"Video2":null,"IP1":null,"PERIODE1":574,"TEXT":null,"parent":{"MNR":"Funktionserweiterung TCS:BUS"},"Audio":[{"features":[{"name":"AnzahlKlingeltasten3938","text":null},{"name":"AnzahlakustischerRufunterscheidungen3933","text":null},{"name":"Mikrofonabsetzbarin4292","text":null},{"name":"LautstaerkeGespraech4008","text":null},{"name":"AnzahlParallelrufe3892","text":null}]}]}},{"node":{"id":"1823","MNR":"FBI4500-0100","Geraeteart4077":"Interface für PTZ-Kameras","Kommunikationstechnologie4164":"TCS:BUS / RS485","Audio1":null,"Video2":true,"IP1":null,"PERIODE1":363,"TEXT":null,"parent":{"MNR":"Funktionserweiterung TCS:BUS"},"Audio":[{"features":[{"name":"AnzahlKlingeltasten3938","text":null},{"name":"AnzahlakustischerRufunterscheidungen3933","text":null},{"name":"Mikrofonabsetzbarin4292","text":null},{"name":"LautstaerkeGespraech4008","text":null},{"name":"AnzahlParallelrufe3892","text":null}]}]}},{"node":{"id":"1836","MNR":"FBO1100-0400","Geraeteart4077":"","Kommunikationstechnologie4164":"TCS:BUS / TK analog","Audio1":true,"Video2":null,"IP1":null,"PERIODE1":340,"TEXT":null,"parent":{"MNR":"Funktionserweiterung TCS:BUS"},"Audio":[{"features":[{"name":"AnzahlKlingeltasten3938","text":null},{"name":"AnzahlakustischerRufunterscheidungen3933","text":null},{"name":"Mikrofonabsetzbarin4292","text":null},{"name":"LautstaerkeGespraech4008","text":null},{"name":"AnzahlParallelrufe3892","text":null}]}]}},{"node":{"id":"1837","MNR":"FBO1110-0400","Geraeteart4077":"","Kommunikationstechnologie4164":"TCS:BUS / TK analog","Audio1":true,"Video2":null,"IP1":null,"PERIODE1":425,"TEXT":null,"parent":{"MNR":"Funktionserweiterung TCS:BUS"},"Audio":[{"features":[{"name":"AnzahlKlingeltasten3938","text":null},{"name":"AnzahlakustischerRufunterscheidungen3933","text":null},{"name":"Mikrofonabsetzbarin4292","text":null},{"name":"LautstaerkeGespraech4008","text":null},{"name":"AnzahlParallelrufe3892","text":null}]},{"features":[null,null,null,{"name":"VerwendungbeiAnzahl Wohneinheitenvon4938","text":null},{"name":"VerwendungbeiAnzahlWohneinheitenbis4939","text":null},{"name":"MAXmoeglicheLasteinheitenAUDIO","text":null}]},{"features":[{"name":"AnzahlKlingeltasten3938","text":null},null,null,null,null,{"name":"Mikrofonabsetzbarin4292","text":null},null,{"name":"LautstaerkeGespraech4008","text":null},null,null,null,null,null,null,null,null,null,null,null,null,null,null,{"name":"VerwendungbeiAnzahl Wohneinheitenvon4938","text":null},{"name":"VerwendungbeiAnzahlWohneinheitenbis4939","text":null},null,{"name":"AkustischeRufunterscheidungen","text":null},null,null,null,null,null]}]}},{"node":{"id":"1841","MNR":"FBO1210-0400","Geraeteart4077":"","Kommunikationstechnologie4164":"TCS:BUS / TK analog","Audio1":true,"Video2":null,"IP1":null,"PERIODE1":1175,"TEXT":null,"parent":{"MNR":"Funktionserweiterung TCS:BUS"},"Audio":[{"features":[{"name":"AnzahlKlingeltasten3938","text":null},{"name":"AnzahlakustischerRufunterscheidungen3933","text":null},{"name":"Mikrofonabsetzbarin4292","text":null},{"name":"LautstaerkeGespraech4008","text":null},{"name":"AnzahlParallelrufe3892","text":null}]}]}},{"node":{"id":"1842","MNR":"FBS1100-0900","Geraeteart4077":"","Kommunikationstechnologie4164":"TCS:BUS","Audio1":null,"Video2":null,"IP1":null,"PERIODE1":85,"TEXT":null,"parent":{"MNR":"Funktionserweiterung TCS:BUS"},"Audio":[{"features":[{"name":"AnzahlKlingeltasten3938","text":null},{"name":"AnzahlakustischerRufunterscheidungen3933","text":null},{"name":"Mikrofonabsetzbarin4292","text":null},{"name":"LautstaerkeGespraech4008","text":null},{"name":"AnzahlParallelrufe3892","text":null}]}]}},{"node":{"id":"1843","MNR":"FBS1105-0900","Geraeteart4077":"Sensor zum Auslösen eines Türöffners / von Steuerfunktionen","Kommunikationstechnologie4164":"TCS:BUS","Audio1":null,"Video2":null,"IP1":null,"PERIODE1":85,"TEXT":null,"parent":{"MNR":"Funktionserweiterung TCS:BUS"},"Audio":[{"features":[{"name":"AnzahlKlingeltasten3938","text":null},{"name":"AnzahlakustischerRufunterscheidungen3933","text":null},{"name":"Mikrofonabsetzbarin4292","text":null},{"name":"LautstaerkeGespraech4008","text":null},{"name":"AnzahlParallelrufe3892","text":null}]},{"features":[null,null,null,{"name":"VerwendungbeiAnzahl Wohneinheitenvon4938","text":null},{"name":"VerwendungbeiAnzahlWohneinheitenbis4939","text":null},{"name":"MAXmoeglicheLasteinheitenAUDIO","text":null}]},{"features":[{"name":"AnzahlKlingeltasten3938","text":null},null,null,null,null,{"name":"Mikrofonabsetzbarin4292","text":null},null,{"name":"LautstaerkeGespraech4008","text":null},null,null,null,null,null,null,null,null,null,null,null,null,null,null,{"name":"VerwendungbeiAnzahl Wohneinheitenvon4938","text":null},{"name":"VerwendungbeiAnzahlWohneinheitenbis4939","text":null},null,{"name":"AkustischeRufunterscheidungen","text":null},null,null,null,null,null]}]}},{"node":{"id":"1847","MNR":"FFI0001-0000","Geraeteart4077":"","Kommunikationstechnologie4164":"","Audio1":true,"Video2":null,"IP1":true,"PERIODE1":41.93,"TEXT":null,"parent":{"MNR":"Funktionserweiterung IP"},"Audio":[{"features":[{"name":"AnzahlKlingeltasten3938","text":null},{"name":"AnzahlakustischerRufunterscheidungen3933","text":null},{"name":"Mikrofonabsetzbarin4292","text":null},{"name":"LautstaerkeGespraech4008","text":null},{"name":"AnzahlParallelrufe3892","text":null}]}]}},{"node":{"id":"1848","MNR":"FFL0002-0000","Geraeteart4077":"Einbau-Sender zum Einbau in die Funksignalgeräte FFL2000-0 und FFL2100-0","Kommunikationstechnologie4164":"TCS:BUS / Funk","Audio1":null,"Video2":null,"IP1":null,"PERIODE1":69,"TEXT":null,"parent":{"MNR":"Funktionserweiterung TCS:BUS"},"Audio":[{"features":[{"name":"AnzahlKlingeltasten3938","text":null},{"name":"AnzahlakustischerRufunterscheidungen3933","text":null},{"name":"Mikrofonabsetzbarin4292","text":null},{"name":"LautstaerkeGespraech4008","text":null},{"name":"AnzahlParallelrufe3892","text":null}]}]}},{"node":{"id":"1849","MNR":"FFL0003-0000","Geraeteart4077":"Steckdosen-Funkgong zur optischen und akustischen Signalisierung eines eingehenden Türrüfs","Kommunikationstechnologie4164":"","Audio1":null,"Video2":null,"IP1":null,"PERIODE1":null,"TEXT":null,"parent":{"MNR":"Funktionserweiterung TCS:BUS"},"Audio":[{"features":[{"name":"AnzahlKlingeltasten3938","text":null},{"name":"AnzahlakustischerRufunterscheidungen3933","text":null},{"name":"Mikrofonabsetzbarin4292","text":null},{"name":"LautstaerkeGespraech4008","text":"einstellbar"},{"name":"AnzahlParallelrufe3892","text":null}]}]}},{"node":{"id":"1850","MNR":"FFL0004-0000","Geraeteart4077":"Einschub-Sender zum Einbau in Geräte der Serien TASTA und 70","Kommunikationstechnologie4164":"TCS:BUS / Funk","Audio1":null,"Video2":null,"IP1":null,"PERIODE1":113,"TEXT":null,"parent":{"MNR":"Funktionserweiterung TCS:BUS"},"Audio":[{"features":[{"name":"AnzahlKlingeltasten3938","text":null},{"name":"AnzahlakustischerRufunterscheidungen3933","text":null},{"name":"Mikrofonabsetzbarin4292","text":null},{"name":"LautstaerkeGespraech4008","text":null},{"name":"AnzahlParallelrufe3892","text":null}]}]}},{"node":{"id":"1851","MNR":"FFL1000-1","Geraeteart4077":"","Kommunikationstechnologie4164":"","Audio1":null,"Video2":null,"IP1":null,"PERIODE1":null,"TEXT":null,"parent":{"MNR":"Funktionserweiterung TCS:BUS"},"Audio":[{"features":[{"name":"AnzahlKlingeltasten3938","text":null},{"name":"AnzahlakustischerRufunterscheidungen3933","text":null},{"name":"Mikrofonabsetzbarin4292","text":null},{"name":"LautstaerkeGespraech4008","text":null},{"name":"AnzahlParallelrufe3892","text":null}]}]}},{"node":{"id":"1852","MNR":"FFL2100-0","Geraeteart4077":"","Kommunikationstechnologie4164":"TCS:BUS / Funk","Audio1":null,"Video2":null,"IP1":null,"PERIODE1":165,"TEXT":null,"parent":{"MNR":"Funktionserweiterung TCS:BUS"},"Audio":[{"features":[{"name":"AnzahlKlingeltasten3938","text":null},{"name":"AnzahlakustischerRufunterscheidungen3933","text":"3 (Marsch, Klingel, Westminster)"},{"name":"Mikrofonabsetzbarin4292","text":null},{"name":"LautstaerkeGespraech4008","text":null},{"name":"AnzahlParallelrufe3892","text":null}]}]}},{"node":{"id":"1853","MNR":"FIL1101-0140","Geraeteart4077":"optisch-akustische Zusatzsignalisierung von Tür- und Internrufen","Kommunikationstechnologie4164":"TCS:BUS","Audio1":null,"Video2":null,"IP1":null,"PERIODE1":107,"TEXT":null,"parent":{"MNR":"Funktionserweiterung TCS:BUS"},"Audio":[{"features":[{"name":"AnzahlKlingeltasten3938","text":null},{"name":"AnzahlakustischerRufunterscheidungen3933","text":"8 (für 2 Haustüren, Etagentür, Internruf und 4 Sub-Türrufe)"},{"name":"Mikrofonabsetzbarin4292","text":null},{"name":"LautstaerkeGespraech4008","text":"einstellbar für Rufton / Durchsage"},{"name":"AnzahlParallelrufe3892","text":"2"}]}]}},{"node":{"id":"1855","MNR":"FIS1100-0600","Geraeteart4077":"für den Anschluss von bis zu 4 Etagentastern / Ausführen von Steuer- und Schaltfunktionen / Umrüstung von Klingelanlagen auf TCS:BUS-Anlagen","Kommunikationstechnologie4164":"TCS:BUS","Audio1":null,"Video2":null,"IP1":null,"PERIODE1":100,"TEXT":null,"parent":{"MNR":"Funktionserweiterung TCS:BUS"},"Audio":[{"features":[{"name":"AnzahlKlingeltasten3938","text":null},{"name":"AnzahlakustischerRufunterscheidungen3933","text":null},{"name":"Mikrofonabsetzbarin4292","text":null},{"name":"LautstaerkeGespraech4008","text":null},{"name":"AnzahlParallelrufe3892","text":null}]},{"features":[null,null,null,{"name":"VerwendungbeiAnzahl Wohneinheitenvon4938","text":null},{"name":"VerwendungbeiAnzahlWohneinheitenbis4939","text":null},{"name":"MAXmoeglicheLasteinheitenAUDIO","text":null}]},{"features":[{"name":"AnzahlKlingeltasten3938","text":null},null,null,null,null,{"name":"Mikrofonabsetzbarin4292","text":null},null,{"name":"LautstaerkeGespraech4008","text":null},null,null,null,null,null,null,null,null,null,null,null,null,null,null,{"name":"VerwendungbeiAnzahl Wohneinheitenvon4938","text":null},{"name":"VerwendungbeiAnzahlWohneinheitenbis4939","text":null},null,{"name":"AkustischeRufunterscheidungen","text":null},null,null,null,null,null]}]}},{"node":{"id":"1867","MNR":"FNA1000-0400","Geraeteart4077":"Multifunktionsgerät mit 10 wählbaren Funktionen Lichtschaltzeit stufenlos einstellbar","Kommunikationstechnologie4164":"","Audio1":null,"Video2":null,"IP1":null,"PERIODE1":115,"TEXT":null,"parent":{"MNR":"Funktionserweiterung TCS:BUS"},"Audio":[{"features":[{"name":"AnzahlKlingeltasten3938","text":null},{"name":"AnzahlakustischerRufunterscheidungen3933","text":null},{"name":"Mikrofonabsetzbarin4292","text":null},{"name":"LautstaerkeGespraech4008","text":null},{"name":"AnzahlParallelrufe3892","text":null}]}]}},{"node":{"id":"1868","MNR":"FVK1202-0","Geraeteart4077":"Variofocus-Kamera","Kommunikationstechnologie4164":"TCS:BUS","Audio1":null,"Video2":true,"IP1":null,"PERIODE1":577,"TEXT":null,"parent":{"MNR":"Funktionserweiterung TCS:BUS"},"Audio":[{"features":[{"name":"AnzahlKlingeltasten3938","text":null},{"name":"AnzahlakustischerRufunterscheidungen3933","text":null},{"name":"Mikrofonabsetzbarin4292","text":null},{"name":"LautstaerkeGespraech4008","text":null},{"name":"AnzahlParallelrufe3892","text":null}]},{"features":[null]}]}},{"node":{"id":"1870","MNR":"FVK2200-0300","Geraeteart4077":"Einbau-Kamera","Kommunikationstechnologie4164":"TCS:BUS","Audio1":null,"Video2":true,"IP1":null,"PERIODE1":424,"TEXT":null,"parent":{"MNR":"Funktionserweiterung TCS:BUS"},"Audio":[{"features":[{"name":"AnzahlKlingeltasten3938","text":null},{"name":"AnzahlakustischerRufunterscheidungen3933","text":null},{"name":"Mikrofonabsetzbarin4292","text":null},{"name":"LautstaerkeGespraech4008","text":null},{"name":"AnzahlParallelrufe3892","text":null}]},{"features":[null]}]}},{"node":{"id":"1872","MNR":"FVK2201-0300","Geraeteart4077":"Zylinder-Kamera","Kommunikationstechnologie4164":"TCS:BUS","Audio1":null,"Video2":true,"IP1":null,"PERIODE1":424,"TEXT":null,"parent":{"MNR":"Funktionserweiterung TCS:BUS"},"Audio":[{"features":[{"name":"AnzahlKlingeltasten3938","text":null},{"name":"AnzahlakustischerRufunterscheidungen3933","text":null},{"name":"Mikrofonabsetzbarin4292","text":null},{"name":"LautstaerkeGespraech4008","text":null},{"name":"AnzahlParallelrufe3892","text":null}]},{"features":[null]}]}},{"node":{"id":"1873","MNR":"FVK2202-0300","Geraeteart4077":"","Kommunikationstechnologie4164":"","Audio1":null,"Video2":true,"IP1":null,"PERIODE1":481,"TEXT":null,"parent":{"MNR":"Funktionserweiterung TCS:BUS"},"Audio":[{"features":[{"name":"AnzahlKlingeltasten3938","text":null},{"name":"AnzahlakustischerRufunterscheidungen3933","text":null},{"name":"Mikrofonabsetzbarin4292","text":null},{"name":"LautstaerkeGespraech4008","text":null},{"name":"AnzahlParallelrufe3892","text":null}]},{"features":[null]}]}},{"node":{"id":"1874","MNR":"FVK3210-0","Geraeteart4077":"Zylinder-Kamera","Kommunikationstechnologie4164":"TCS:BUS","Audio1":null,"Video2":true,"IP1":null,"PERIODE1":468,"TEXT":null,"parent":{"MNR":"Funktionserweiterung TCS:BUS"},"Audio":[{"features":[{"name":"AnzahlKlingeltasten3938","text":null},{"name":"AnzahlakustischerRufunterscheidungen3933","text":null},{"name":"Mikrofonabsetzbarin4292","text":null},{"name":"LautstaerkeGespraech4008","text":null},{"name":"AnzahlParallelrufe3892","text":null}]},{"features":[null]}]}},{"node":{"id":"1875","MNR":"FVK3220-0","Geraeteart4077":"Zylinder-Kamera","Kommunikationstechnologie4164":"TCS:BUS","Audio1":null,"Video2":true,"IP1":null,"PERIODE1":468,"TEXT":null,"parent":{"MNR":"Funktionserweiterung TCS:BUS"},"Audio":[{"features":[{"name":"AnzahlKlingeltasten3938","text":null},{"name":"AnzahlakustischerRufunterscheidungen3933","text":null},{"name":"Mikrofonabsetzbarin4292","text":null},{"name":"LautstaerkeGespraech4008","text":null},{"name":"AnzahlParallelrufe3892","text":null}]},{"features":[null]}]}},{"node":{"id":"1876","MNR":"FVK3230-0","Geraeteart4077":"Zylinder-Kamera","Kommunikationstechnologie4164":"TCS:BUS","Audio1":null,"Video2":true,"IP1":null,"PERIODE1":468,"TEXT":null,"parent":{"MNR":"Funktionserweiterung TCS:BUS"},"Audio":[{"features":[{"name":"AnzahlKlingeltasten3938","text":null},{"name":"AnzahlakustischerRufunterscheidungen3933","text":null},{"name":"Mikrofonabsetzbarin4292","text":null},{"name":"LautstaerkeGespraech4008","text":null},{"name":"AnzahlParallelrufe3892","text":null}]},{"features":[null]}]}},{"node":{"id":"1877","MNR":"FVK3240-0","Geraeteart4077":"Zylinder-Kamera","Kommunikationstechnologie4164":"TCS:BUS","Audio1":null,"Video2":true,"IP1":null,"PERIODE1":468,"TEXT":null,"parent":{"MNR":"Funktionserweiterung TCS:BUS"},"Audio":[{"features":[{"name":"AnzahlKlingeltasten3938","text":null},{"name":"AnzahlakustischerRufunterscheidungen3933","text":null},{"name":"Mikrofonabsetzbarin4292","text":null},{"name":"LautstaerkeGespraech4008","text":null},{"name":"AnzahlParallelrufe3892","text":null}]},{"features":[null]}]}},{"node":{"id":"1881","MNR":"FVK4224-0","Geraeteart4077":"Dome-Kamera","Kommunikationstechnologie4164":"TCS:BUS","Audio1":null,"Video2":true,"IP1":null,"PERIODE1":577,"TEXT":null,"parent":{"MNR":"Funktionserweiterung TCS:BUS"},"Audio":[{"features":[{"name":"AnzahlKlingeltasten3938","text":null},{"name":"AnzahlakustischerRufunterscheidungen3933","text":null},{"name":"Mikrofonabsetzbarin4292","text":null},{"name":"LautstaerkeGespraech4008","text":null},{"name":"AnzahlParallelrufe3892","text":null}]},{"features":[null]}]}},{"node":{"id":"1882","MNR":"FVK4225-0","Geraeteart4077":"Dome-Kamera","Kommunikationstechnologie4164":"TCS:BUS","Audio1":null,"Video2":true,"IP1":null,"PERIODE1":669,"TEXT":null,"parent":{"MNR":"Funktionserweiterung TCS:BUS"},"Audio":[{"features":[{"name":"AnzahlKlingeltasten3938","text":null},{"name":"AnzahlakustischerRufunterscheidungen3933","text":null},{"name":"Mikrofonabsetzbarin4292","text":null},{"name":"LautstaerkeGespraech4008","text":null},{"name":"AnzahlParallelrufe3892","text":null}]},{"features":[null]}]}},{"node":{"id":"1886","MNR":"FVU1200-0600","Geraeteart4077":"zur gezielten Umschaltung zwischen Etagen-Video-Außenstation und Haupt-Video-Außenstation auf eine Video-Innenstation","Kommunikationstechnologie4164":"TCS:BUS","Audio1":null,"Video2":true,"IP1":null,"PERIODE1":195,"TEXT":null,"parent":{"MNR":"Funktionserweiterung TCS:BUS"},"Audio":[{"features":[{"name":"AnzahlKlingeltasten3938","text":null},{"name":"AnzahlakustischerRufunterscheidungen3933","text":null},{"name":"Mikrofonabsetzbarin4292","text":null},{"name":"LautstaerkeGespraech4008","text":null},{"name":"AnzahlParallelrufe3892","text":null}]}]}},{"node":{"id":"1888","MNR":"FVU1210-0600","Geraeteart4077":"zur gezielten Auswahl von 1 aus bis zu 2 Kameras","Kommunikationstechnologie4164":"TCS:BUS","Audio1":null,"Video2":true,"IP1":null,"PERIODE1":195,"TEXT":null,"parent":{"MNR":"Funktionserweiterung TCS:BUS"},"Audio":[{"features":[{"name":"AnzahlKlingeltasten3938","text":null},{"name":"AnzahlakustischerRufunterscheidungen3933","text":null},{"name":"Mikrofonabsetzbarin4292","text":null},{"name":"LautstaerkeGespraech4008","text":null},{"name":"AnzahlParallelrufe3892","text":null}]}]}},{"node":{"id":"1889","MNR":"FVU1401-0400","Geraeteart4077":"zur gezielten Auswahl von 1 aus bis zu 64 Kameras","Kommunikationstechnologie4164":"TCS:BUS","Audio1":null,"Video2":true,"IP1":null,"PERIODE1":490,"TEXT":null,"parent":{"MNR":"Funktionserweiterung TCS:BUS"},"Audio":[{"features":[{"name":"AnzahlKlingeltasten3938","text":null},{"name":"AnzahlakustischerRufunterscheidungen3933","text":null},{"name":"Mikrofonabsetzbarin4292","text":null},{"name":"LautstaerkeGespraech4008","text":null},{"name":"AnzahlParallelrufe3892","text":null}]}]}},{"node":{"id":"1892","MNR":"FVW1001-0600","Geraeteart4077":"zum Umwandeln eines symmetrischen Videosignals in ein asymmetrischen Videosignals","Kommunikationstechnologie4164":"","Audio1":null,"Video2":true,"IP1":null,"PERIODE1":250,"TEXT":null,"parent":{"MNR":"Funktionserweiterung TCS:BUS"},"Audio":[{"features":[{"name":"AnzahlKlingeltasten3938","text":null},{"name":"AnzahlakustischerRufunterscheidungen3933","text":null},{"name":"Mikrofonabsetzbarin4292","text":null},{"name":"LautstaerkeGespraech4008","text":null},{"name":"AnzahlParallelrufe3892","text":null}]}]}},{"node":{"id":"1894","MNR":"FVW2000-0600","Geraeteart4077":"zur Anschaltung von Kameras anderer Hersteller an TCS-Videoanlagen","Kommunikationstechnologie4164":"TCS:BUS","Audio1":null,"Video2":true,"IP1":null,"PERIODE1":165,"TEXT":null,"parent":{"MNR":"Funktionserweiterung TCS:BUS"},"Audio":[{"features":[{"name":"AnzahlKlingeltasten3938","text":null},{"name":"AnzahlakustischerRufunterscheidungen3933","text":null},{"name":"Mikrofonabsetzbarin4292","text":null},{"name":"LautstaerkeGespraech4008","text":null},{"name":"AnzahlParallelrufe3892","text":null}]},{"features":[null]}]}},{"node":{"id":"1896","MNR":"FVW3030-0600","Geraeteart4077":"zur Anschaltung von Video-6-Draht Außenstationen an Video-2-Draht-Anlagen","Kommunikationstechnologie4164":"TCS:BUS / Video-2-Draht","Audio1":null,"Video2":true,"IP1":null,"PERIODE1":120,"TEXT":null,"parent":{"MNR":"Funktionserweiterung V2D"},"Audio":[{"features":[{"name":"AnzahlKlingeltasten3938","text":null},{"name":"AnzahlakustischerRufunterscheidungen3933","text":null},{"name":"Mikrofonabsetzbarin4292","text":null},{"name":"LautstaerkeGespraech4008","text":null},{"name":"AnzahlParallelrufe3892","text":null}]}]}},{"node":{"id":"1899","MNR":"FVW3040-0600","Geraeteart4077":"zur Anschaltung von alten TCS:BUS-Audio-Innenstationen an Video-2-Draht-Anlagen","Kommunikationstechnologie4164":"TCS:BUS / Video-2-Draht","Audio1":null,"Video2":true,"IP1":null,"PERIODE1":null,"TEXT":null,"parent":{"MNR":"Funktionserweiterung V2D"},"Audio":[{"features":[{"name":"AnzahlKlingeltasten3938","text":null},{"name":"AnzahlakustischerRufunterscheidungen3933","text":null},{"name":"Mikrofonabsetzbarin4292","text":null},{"name":"LautstaerkeGespraech4008","text":null},{"name":"AnzahlParallelrufe3892","text":null}]}]}},{"node":{"id":"1902","MNR":"FVY1200-0400","Geraeteart4077":"zur Aufsplittung von Videosträngen","Kommunikationstechnologie4164":"TCS:BUS","Audio1":null,"Video2":true,"IP1":null,"PERIODE1":120,"TEXT":null,"parent":{"MNR":"Funktionserweiterung TCS:BUS"},"Audio":[{"features":[{"name":"AnzahlKlingeltasten3938","text":null},{"name":"AnzahlakustischerRufunterscheidungen3933","text":null},{"name":"Mikrofonabsetzbarin4292","text":null},{"name":"LautstaerkeGespraech4008","text":null},{"name":"AnzahlParallelrufe3892","text":null}]},{"features":[null,null,null,{"name":"VerwendungbeiAnzahl Wohneinheitenvon4938","text":null},{"name":"VerwendungbeiAnzahlWohneinheitenbis4939","text":null},{"name":"MAXmoeglicheLasteinheitenAUDIO","text":null}]},{"features":[{"name":"AnzahlKlingeltasten3938","text":null},null,null,null,null,{"name":"Mikrofonabsetzbarin4292","text":null},null,{"name":"LautstaerkeGespraech4008","text":null},null,null,null,null,null,null,null,null,null,null,null,null,null,null,{"name":"VerwendungbeiAnzahl Wohneinheitenvon4938","text":null},{"name":"VerwendungbeiAnzahlWohneinheitenbis4939","text":null},null,{"name":"AkustischeRufunterscheidungen","text":null},null,null,null,null,null]}]}},{"node":{"id":"1903","MNR":"FVY1200-0600","Geraeteart4077":"zur Aufsplittung von Videosträngen","Kommunikationstechnologie4164":"TCS:BUS","Audio1":null,"Video2":true,"IP1":null,"PERIODE1":120,"TEXT":null,"parent":{"MNR":"Funktionserweiterung TCS:BUS"},"Audio":[{"features":[{"name":"AnzahlKlingeltasten3938","text":null},{"name":"AnzahlakustischerRufunterscheidungen3933","text":null},{"name":"Mikrofonabsetzbarin4292","text":null},{"name":"LautstaerkeGespraech4008","text":null},{"name":"AnzahlParallelrufe3892","text":null}]}]}},{"node":{"id":"1907","MNR":"FVY1400-0400","Geraeteart4077":"zur Aufsplittung von Videosträngen","Kommunikationstechnologie4164":"TCS:BUS","Audio1":null,"Video2":true,"IP1":null,"PERIODE1":225,"TEXT":null,"parent":{"MNR":"Funktionserweiterung TCS:BUS"},"Audio":[{"features":[{"name":"AnzahlKlingeltasten3938","text":null},{"name":"AnzahlakustischerRufunterscheidungen3933","text":null},{"name":"Mikrofonabsetzbarin4292","text":null},{"name":"LautstaerkeGespraech4008","text":null},{"name":"AnzahlParallelrufe3892","text":null}]},{"features":[null,null,null,{"name":"VerwendungbeiAnzahl Wohneinheitenvon4938","text":null},{"name":"VerwendungbeiAnzahlWohneinheitenbis4939","text":null},{"name":"MAXmoeglicheLasteinheitenAUDIO","text":null}]},{"features":[{"name":"AnzahlKlingeltasten3938","text":null},null,null,null,null,{"name":"Mikrofonabsetzbarin4292","text":null},null,{"name":"LautstaerkeGespraech4008","text":null},null,null,null,null,null,null,null,null,null,null,null,null,null,null,{"name":"VerwendungbeiAnzahl Wohneinheitenvon4938","text":null},{"name":"VerwendungbeiAnzahlWohneinheitenbis4939","text":null},null,{"name":"AkustischeRufunterscheidungen","text":null},null,null,null,null,null]}]}},{"node":{"id":"1910","MNR":"FVY3200-0600","Geraeteart4077":"","Kommunikationstechnologie4164":"Video-2-Draht","Audio1":null,"Video2":true,"IP1":null,"PERIODE1":120,"TEXT":null,"parent":{"MNR":"Funktionserweiterung V2D"},"Audio":[{"features":[{"name":"AnzahlKlingeltasten3938","text":null},{"name":"AnzahlakustischerRufunterscheidungen3933","text":null},{"name":"Mikrofonabsetzbarin4292","text":null},{"name":"LautstaerkeGespraech4008","text":null},{"name":"AnzahlParallelrufe3892","text":null}]},{"features":[{"name":"AnzahlKlingeltasten3938","text":null},null,null,null,null,{"name":"Mikrofonabsetzbarin4292","text":null},null,{"name":"LautstaerkeGespraech4008","text":null},null,null,null,null,null,null,null,null,null,null,null,null,null,null,{"name":"VerwendungbeiAnzahl Wohneinheitenvon4938","text":null},{"name":"VerwendungbeiAnzahlWohneinheitenbis4939","text":null},null,{"name":"AkustischeRufunterscheidungen","text":null},null,null,null,null,null]}]}},{"node":{"id":"2460","MNR":"PC1-I","Geraeteart4077":"","Kommunikationstechnologie4164":"","Audio1":true,"Video2":null,"IP1":null,"PERIODE1":1863,"TEXT":null,"parent":{"MNR":"Funktionserweiterung TCS:BUS"},"Audio":[{"features":[{"name":"AnzahlKlingeltasten3938","text":null},{"name":"AnzahlakustischerRufunterscheidungen3933","text":null},{"name":"Mikrofonabsetzbarin4292","text":null},{"name":"LautstaerkeGespraech4008","text":null},{"name":"AnzahlParallelrufe3892","text":null}]}]}},{"node":{"id":"3208","MNR":"SK10-SG","Geraeteart4077":"","Kommunikationstechnologie4164":"TCS:BUS","Audio1":null,"Video2":null,"IP1":null,"PERIODE1":452,"TEXT":null,"parent":{"MNR":"Funktionserweiterung TCS:BUS"},"Audio":[{"features":[{"name":"AnzahlKlingeltasten3938","text":null},{"name":"AnzahlakustischerRufunterscheidungen3933","text":null},{"name":"Mikrofonabsetzbarin4292","text":null},{"name":"LautstaerkeGespraech4008","text":null},{"name":"AnzahlParallelrufe3892","text":null}]}]}},{"node":{"id":"3279","MNR":"TOER2-EB","Geraeteart4077":"Türöffner-Relais für gezieltes Türöffnen bei mehr als einer Außenstation","Kommunikationstechnologie4164":"TCS:BUS","Audio1":null,"Video2":null,"IP1":null,"PERIODE1":90,"TEXT":null,"parent":{"MNR":"Funktionserweiterung TCS:BUS"},"Audio":[{"features":[{"name":"AnzahlKlingeltasten3938","text":null},{"name":"AnzahlakustischerRufunterscheidungen3933","text":null},{"name":"Mikrofonabsetzbarin4292","text":null},{"name":"LautstaerkeGespraech4008","text":null},{"name":"AnzahlParallelrufe3892","text":null}]},{"features":[null,null,null,{"name":"VerwendungbeiAnzahl Wohneinheitenvon4938","text":null},{"name":"VerwendungbeiAnzahlWohneinheitenbis4939","text":null},{"name":"MAXmoeglicheLasteinheitenAUDIO","text":null}]},{"features":[{"name":"AnzahlKlingeltasten3938","text":null},null,null,null,null,{"name":"Mikrofonabsetzbarin4292","text":null},null,{"name":"LautstaerkeGespraech4008","text":null},null,null,null,null,null,null,null,null,null,null,null,null,null,null,{"name":"VerwendungbeiAnzahl Wohneinheitenvon4938","text":null},{"name":"VerwendungbeiAnzahlWohneinheitenbis4939","text":null},null,{"name":"AkustischeRufunterscheidungen","text":null},null,null,null,null,null]}]}},{"node":{"id":"3281","MNR":"TRE1-EB","Geraeteart4077":"Einbau-Ruf-Relais für TCS-Innenstationen zur gezielten Ansteuerung von bauseitigen Signalgeräten","Kommunikationstechnologie4164":"TCS:BUS","Audio1":null,"Video2":null,"IP1":null,"PERIODE1":50,"TEXT":null,"parent":{"MNR":"Funktionserweiterung TCS:BUS"},"Audio":[{"features":[{"name":"AnzahlKlingeltasten3938","text":null},{"name":"AnzahlakustischerRufunterscheidungen3933","text":null},{"name":"Mikrofonabsetzbarin4292","text":null},{"name":"LautstaerkeGespraech4008","text":null},{"name":"AnzahlParallelrufe3892","text":null}]}]}},{"node":{"id":"3282","MNR":"TRE2-EB","Geraeteart4077":"Ruf-Relais zur Ansteuerung von bauseitigen Signalgeräten Auswertung von Sonderfunktionen einer Innenstation möglich","Kommunikationstechnologie4164":"TCS:BUS","Audio1":null,"Video2":null,"IP1":null,"PERIODE1":90,"TEXT":null,"parent":{"MNR":"Funktionserweiterung TCS:BUS"},"Audio":[{"features":[{"name":"AnzahlKlingeltasten3938","text":null},{"name":"AnzahlakustischerRufunterscheidungen3933","text":null},{"name":"Mikrofonabsetzbarin4292","text":null},{"name":"LautstaerkeGespraech4008","text":null},{"name":"AnzahlParallelrufe3892","text":null}]},{"features":[null,null,null,{"name":"VerwendungbeiAnzahl Wohneinheitenvon4938","text":null},{"name":"VerwendungbeiAnzahlWohneinheitenbis4939","text":null},{"name":"MAXmoeglicheLasteinheitenAUDIO","text":null}]},{"features":[{"name":"AnzahlKlingeltasten3938","text":null},null,null,null,null,{"name":"Mikrofonabsetzbarin4292","text":null},null,{"name":"LautstaerkeGespraech4008","text":null},null,null,null,null,null,null,null,null,null,null,null,null,null,null,{"name":"VerwendungbeiAnzahl Wohneinheitenvon4938","text":null},{"name":"VerwendungbeiAnzahlWohneinheitenbis4939","text":null},null,{"name":"AkustischeRufunterscheidungen","text":null},null,null,null,null,null]}]}},{"node":{"id":"3462","MNR":"VKA10-GH","Geraeteart4077":"","Kommunikationstechnologie4164":"","Audio1":null,"Video2":true,"IP1":null,"PERIODE1":null,"TEXT":null,"parent":{"MNR":"Funktionserweiterung TCS:BUS"},"Audio":[{"features":[{"name":"AnzahlKlingeltasten3938","text":null},{"name":"AnzahlakustischerRufunterscheidungen3933","text":null},{"name":"Mikrofonabsetzbarin4292","text":null},{"name":"LautstaerkeGespraech4008","text":null},{"name":"AnzahlParallelrufe3892","text":null}]},{"features":[null]}]}},{"node":{"id":"3612","MNR":"Funktionserweiterung TCS:BUS","Geraeteart4077":"","Kommunikationstechnologie4164":"","Audio1":null,"Video2":null,"IP1":null,"PERIODE1":null,"TEXT":null,"parent":{"MNR":"Funktionserweiterung TCS:BUS"},"Audio":[{"features":[{"name":"AnzahlKlingeltasten3938","text":null},{"name":"AnzahlakustischerRufunterscheidungen3933","text":null},{"name":"Mikrofonabsetzbarin4292","text":null},{"name":"LautstaerkeGespraech4008","text":null},{"name":"AnzahlParallelrufe3892","text":null}]}]}},{"node":{"id":"3613","MNR":"Funktionserweiterung TCS:BUS","Geraeteart4077":"","Kommunikationstechnologie4164":"","Audio1":null,"Video2":true,"IP1":null,"PERIODE1":null,"TEXT":null,"parent":{"MNR":"Funktionserweiterung TCS:BUS"},"Audio":[{"features":[{"name":"AnzahlKlingeltasten3938","text":null},{"name":"AnzahlakustischerRufunterscheidungen3933","text":null},{"name":"Mikrofonabsetzbarin4292","text":null},{"name":"LautstaerkeGespraech4008","text":null},{"name":"AnzahlParallelrufe3892","text":null}]}]}},{"node":{"id":"3614","MNR":"Funktionserweiterung TCS:BUS","Geraeteart4077":"","Kommunikationstechnologie4164":"","Audio1":null,"Video2":null,"IP1":null,"PERIODE1":null,"TEXT":null,"parent":{"MNR":"Funktionserweiterung TCS:BUS"},"Audio":[{"features":[{"name":"AnzahlKlingeltasten3938","text":null},{"name":"AnzahlakustischerRufunterscheidungen3933","text":null},{"name":"Mikrofonabsetzbarin4292","text":null},{"name":"LautstaerkeGespraech4008","text":null},{"name":"AnzahlParallelrufe3892","text":null}]}]}},{"node":{"id":"4455","MNR":"FAA1100-0400","Geraeteart4077":"","Kommunikationstechnologie4164":"","Audio1":null,"Video2":null,"IP1":null,"PERIODE1":null,"TEXT":null,"parent":{"MNR":"Funktionserweiterung TCS:BUS"},"Audio":[{"features":[{"name":"AnzahlKlingeltasten3938","text":null},{"name":"AnzahlakustischerRufunterscheidungen3933","text":null},{"name":"Mikrofonabsetzbarin4292","text":null},{"name":"LautstaerkeGespraech4008","text":null},{"name":"AnzahlParallelrufe3892","text":null}]}]}},{"node":{"id":"6400","MNR":"FBO1200-0400","Geraeteart4077":"","Kommunikationstechnologie4164":"TCS:BUS / TK analog","Audio1":true,"Video2":null,"IP1":null,"PERIODE1":null,"TEXT":null,"parent":{"MNR":"Funktionserweiterung TCS:BUS"},"Audio":[{"features":[{"name":"AnzahlKlingeltasten3938","text":null},{"name":"AnzahlakustischerRufunterscheidungen3933","text":null},{"name":"Mikrofonabsetzbarin4292","text":null},{"name":"LautstaerkeGespraech4008","text":null},{"name":"AnzahlParallelrufe3892","text":null}]}]}},{"node":{"id":"6401","MNR":"FBP2000-0000","Geraeteart4077":"","Kommunikationstechnologie4164":"","Audio1":null,"Video2":null,"IP1":null,"PERIODE1":null,"TEXT":null,"parent":{"MNR":"Funktionserweiterung TCS:BUS"},"Audio":[{"features":[{"name":"AnzahlKlingeltasten3938","text":null},{"name":"AnzahlakustischerRufunterscheidungen3933","text":null},{"name":"Mikrofonabsetzbarin4292","text":null},{"name":"LautstaerkeGespraech4008","text":null},{"name":"AnzahlParallelrufe3892","text":null}]}]}},{"node":{"id":"6402","MNR":"FFL0001-0000","Geraeteart4077":"Steckdosen-Funkgong zur optischen und akustischen Signalisierung eines eingehenden Türrüfs","Kommunikationstechnologie4164":"Funk","Audio1":null,"Video2":null,"IP1":null,"PERIODE1":91,"TEXT":null,"parent":{"MNR":"Funktionserweiterung TCS:BUS"},"Audio":[{"features":[{"name":"AnzahlKlingeltasten3938","text":null},{"name":"AnzahlakustischerRufunterscheidungen3933","text":"3 (Marsch, Klingel, Westminster)"},{"name":"Mikrofonabsetzbarin4292","text":null},{"name":"LautstaerkeGespraech4008","text":null},{"name":"AnzahlParallelrufe3892","text":null}]}]}},{"node":{"id":"6403","MNR":"FFL2000-0","Geraeteart4077":"","Kommunikationstechnologie4164":"TCS:BUS / Funk","Audio1":null,"Video2":null,"IP1":null,"PERIODE1":173,"TEXT":null,"parent":{"MNR":"Funktionserweiterung TCS:BUS"},"Audio":[{"features":[{"name":"AnzahlKlingeltasten3938","text":null},{"name":"AnzahlakustischerRufunterscheidungen3933","text":"3 (Marsch, Klingel, Westminster)"},{"name":"Mikrofonabsetzbarin4292","text":null},{"name":"LautstaerkeGespraech4008","text":null},{"name":"AnzahlParallelrufe3892","text":null}]}]}},{"node":{"id":"6404","MNR":"FFL2200-0","Geraeteart4077":"","Kommunikationstechnologie4164":"TCS:BUS / Funk","Audio1":null,"Video2":null,"IP1":null,"PERIODE1":184,"TEXT":null,"parent":{"MNR":"Funktionserweiterung TCS:BUS"},"Audio":[{"features":[{"name":"AnzahlKlingeltasten3938","text":null},{"name":"AnzahlakustischerRufunterscheidungen3933","text":"3 (Marsch, Klingel, Westminster)"},{"name":"Mikrofonabsetzbarin4292","text":null},{"name":"LautstaerkeGespraech4008","text":null},{"name":"AnzahlParallelrufe3892","text":null}]}]}},{"node":{"id":"6405","MNR":"FIL5100-0145","Geraeteart4077":"","Kommunikationstechnologie4164":"","Audio1":null,"Video2":null,"IP1":null,"PERIODE1":null,"TEXT":null,"parent":{"MNR":"Funktionserweiterung TCS:BUS"},"Audio":[{"features":[{"name":"AnzahlKlingeltasten3938","text":null},{"name":"AnzahlakustischerRufunterscheidungen3933","text":null},{"name":"Mikrofonabsetzbarin4292","text":null},{"name":"LautstaerkeGespraech4008","text":null},{"name":"AnzahlParallelrufe3892","text":null}]}]}},{"node":{"id":"6406","MNR":"VSW05-SG","Geraeteart4077":"","Kommunikationstechnologie4164":"","Audio1":null,"Video2":true,"IP1":null,"PERIODE1":null,"TEXT":null,"parent":{"MNR":"Funktionserweiterung TCS:BUS"},"Audio":[{"features":[{"name":"AnzahlKlingeltasten3938","text":null},{"name":"AnzahlakustischerRufunterscheidungen3933","text":null},{"name":"Mikrofonabsetzbarin4292","text":null},{"name":"LautstaerkeGespraech4008","text":null},{"name":"AnzahlParallelrufe3892","text":null}]}]}},{"node":{"id":"6415","MNR":"FFL0005-0000","Geraeteart4077":"Steckdosen-Funkgong zur optischen und akustischen Signalisierung eines eingehenden Türrüfs","Kommunikationstechnologie4164":"Funk","Audio1":null,"Video2":null,"IP1":null,"PERIODE1":110,"TEXT":null,"parent":{"MNR":"Funktionserweiterung TCS:BUS"},"Audio":[{"features":[{"name":"AnzahlKlingeltasten3938","text":null},{"name":"AnzahlakustischerRufunterscheidungen3933","text":"8"},{"name":"Mikrofonabsetzbarin4292","text":null},{"name":"LautstaerkeGespraech4008","text":null},{"name":"AnzahlParallelrufe3892","text":null}]}]}},{"node":{"id":"6427","MNR":"FFL3000-0","Geraeteart4077":"Gerätekombination aus Einbau-Sender, Steckdosen-Funkgong und Einbau-Ruf-Relais zur \noptisch-akustische Signalisierung eines Türrüfs","Kommunikationstechnologie4164":"TCS:BUS / Funk","Audio1":null,"Video2":null,"IP1":null,"PERIODE1":210,"TEXT":null,"parent":{"MNR":"Funktionserweiterung TCS:BUS"},"Audio":[{"features":[{"name":"AnzahlKlingeltasten3938","text":null},{"name":"AnzahlakustischerRufunterscheidungen3933","text":"8"},{"name":"Mikrofonabsetzbarin4292","text":null},{"name":"LautstaerkeGespraech4008","text":null},{"name":"AnzahlParallelrufe3892","text":null}]}]}},{"node":{"id":"6428","MNR":"FFL3100-0","Geraeteart4077":"Gerätekombination aus Einbau-Sender, Steckdosen-Funkgong und Einbau-Ruf-Relais zur \noptisch-akustische Signalisierung eines Türrüfs","Kommunikationstechnologie4164":"TCS:BUS / Funk","Audio1":null,"Video2":null,"IP1":null,"PERIODE1":210,"TEXT":null,"parent":{"MNR":"Funktionserweiterung TCS:BUS"},"Audio":[{"features":[{"name":"AnzahlKlingeltasten3938","text":null},{"name":"AnzahlakustischerRufunterscheidungen3933","text":"8"},{"name":"Mikrofonabsetzbarin4292","text":null},{"name":"LautstaerkeGespraech4008","text":null},{"name":"AnzahlParallelrufe3892","text":null}]}]}},{"node":{"id":"6429","MNR":"FFL3200-0","Geraeteart4077":"Gerätekombination aus Einschub-Funksendeplatine RTS9004E und Steckdosen-Funkgong RCP24E zur optisch-akustische Signalisierung eines Türrüfs","Kommunikationstechnologie4164":"TCS:BUS / Funk","Audio1":null,"Video2":null,"IP1":null,"PERIODE1":210,"TEXT":null,"parent":{"MNR":"Funktionserweiterung TCS:BUS"},"Audio":[{"features":[{"name":"AnzahlKlingeltasten3938","text":null},{"name":"AnzahlakustischerRufunterscheidungen3933","text":"8"},{"name":"Mikrofonabsetzbarin4292","text":null},{"name":"LautstaerkeGespraech4008","text":null},{"name":"AnzahlParallelrufe3892","text":null}]}]}},{"node":{"id":"7155","MNR":"FEZ1000-0400","Geraeteart4077":"","Kommunikationstechnologie4164":"","Audio1":false,"Video2":false,"IP1":true,"PERIODE1":1136,"TEXT":"<p>Main function: Management and monitoring of building communication of up to 150 devices.<br />\nPurpose: Intercom, video surveillance, access control, switching, mobile door communication via apps.<br />\nConnection options: Local connections, optional connection to snipdoo CLOUD for mobile door communication.<br />\nDevice management: Supports cameras, intercoms, SIP devices, actuators<br />\nDimensions: 105mm x 90mm x 70mm (WxHxD), mounting type DIN rail (top-hat rail) 6TE, power supply 24V DC<br />\nNetwork interfaces: LAN (RJ45, IEEE802.3u 10/100BASE-Tx/s, Auto MDIX), supports IPv4, ARP, ICMP, UDP, TCP, DNS, DHCP, HTTP, WS, WSS, SIP, TLS, RTP, SNTP.<br />\nActuator functions: Control of 2 actuators (e.g. light, door opener), switching options: NO, NC, COM<br />\nOperating environment: Temperature range from 0°C to 40°C</p>\n","parent":{"MNR":"Funktionserweiterung IP"},"Audio":[{"features":[{"name":"AnzahlKlingeltasten3938","text":null},{"name":"AnzahlakustischerRufunterscheidungen3933","text":null},{"name":"Mikrofonabsetzbarin4292","text":null},{"name":"LautstaerkeGespraech4008","text":null},{"name":"AnzahlParallelrufe3892","text":null}]}]}},{"node":{"id":"7216","MNR":"FBI5100-0400","Geraeteart4077":"","Kommunikationstechnologie4164":"","Audio1":null,"Video2":null,"IP1":null,"PERIODE1":559,"TEXT":"TCS ELA-Interface FBI5100-0400 <br/><br/>Hersteller: TCS TürControlSysteme AG<br/>Produktion: Made in Germany<br/>Artikelnummer: FBI5100-0400<br/><br/>GERÄTEEIGENSCHAFTEN<br/>Kopplung einer TCS-Türsprechanlage mit einer<br/>elektroakustischen Anlage (ELA)<br/>LED-Anzeige<br/>Einzeldurchsage nach Internruf<br/>Rufton / Sprachlautstärke: manuell einstellbar<br/>Anzahl Drähte: 3-Draht notwendig<br/>Konfiguration: mit TCSK / configo<br/><br/>TECHNISCHE DATEN  <br/>Technologie: 2-Draht TCS:BUS<br/>Schutzart: IP20<br/>Versorgungsspannung: 24 V<br/>Eingangsstrom: max. 40 mA<br/>Reiheneinbaugehäuse HxBxT mm: 90x72x70<br/>zulässige Umgebungstemperatur: 0 bis +40 °C<br/><br/>","parent":{"MNR":"Funktionserweiterung TCS:BUS"},"Audio":[{"features":[{"name":"AnzahlKlingeltasten3938","text":null},{"name":"AnzahlakustischerRufunterscheidungen3933","text":null},{"name":"Mikrofonabsetzbarin4292","text":null},{"name":"LautstaerkeGespraech4008","text":null},{"name":"AnzahlParallelrufe3892","text":null}]}]}},{"node":{"id":"12856","MNR":"FVK4215-0","Geraeteart4077":"","Kommunikationstechnologie4164":"","Audio1":null,"Video2":true,"IP1":null,"PERIODE1":485,"TEXT":null,"parent":{"MNR":"Funktionserweiterung TCS:BUS"},"Audio":[{"features":[{"name":"AnzahlKlingeltasten3938","text":null},{"name":"AnzahlakustischerRufunterscheidungen3933","text":null},{"name":"Mikrofonabsetzbarin4292","text":null},{"name":"LautstaerkeGespraech4008","text":null},{"name":"AnzahlParallelrufe3892","text":null}]},{"features":[null]}]}},{"node":{"id":"13237","MNR":"FAA3100-0300","Geraeteart4077":"","Kommunikationstechnologie4164":"","Audio1":null,"Video2":null,"IP1":null,"PERIODE1":88,"TEXT":null,"parent":{"MNR":"Funktionserweiterung TCS:BUS"},"Audio":[{"features":[{"name":"AnzahlKlingeltasten3938","text":null},{"name":"AnzahlakustischerRufunterscheidungen3933","text":null},{"name":"Mikrofonabsetzbarin4292","text":null},{"name":"LautstaerkeGespraech4008","text":null},{"name":"AnzahlParallelrufe3892","text":null}]}]}},{"node":{"id":"13259","MNR":"FFI0002-0000","Geraeteart4077":"","Kommunikationstechnologie4164":"","Audio1":true,"Video2":null,"IP1":true,"PERIODE1":66.39,"TEXT":null,"parent":{"MNR":"Funktionserweiterung IP"},"Audio":[{"features":[{"name":"AnzahlKlingeltasten3938","text":null},{"name":"AnzahlakustischerRufunterscheidungen3933","text":null},{"name":"Mikrofonabsetzbarin4292","text":null},{"name":"LautstaerkeGespraech4008","text":null},{"name":"AnzahlParallelrufe3892","text":null}]}]}},{"node":{"id":"16355","MNR":"KBRE2-SG","Geraeteart4077":"","Kommunikationstechnologie4164":"","Audio1":null,"Video2":null,"IP1":null,"PERIODE1":null,"TEXT":null,"parent":{"MNR":"Funktionserweiterung TCS:BUS"},"Audio":[{"features":[{"name":"AnzahlKlingeltasten3938","text":null},{"name":"AnzahlakustischerRufunterscheidungen3933","text":null},{"name":"Mikrofonabsetzbarin4292","text":null},{"name":"LautstaerkeGespraech4008","text":null},{"name":"AnzahlParallelrufe3892","text":null}]}]}}]}}}